NOTICE.md
qtvscodestyle/__init__.py
qtvscodestyle/base.py
qtvscodestyle/const.py
qtvscodestyle/examples/__init__.py
qtvscodestyle/examples/activitybar/__init__.py
qtvscodestyle/examples/activitybar/__main__.py
qtvscodestyle/examples/icon_browser/__init__.py
qtvscodestyle/examples/icon_browser/__main__.py
qtvscodestyle/examples/line/__init__.py
qtvscodestyle/examples/line/__main__.py
qtvscodestyle/examples/lineedit/__init__.py
qtvscodestyle/examples/lineedit/__main__.py
qtvscodestyle/examples/pushbutton/__init__.py
qtvscodestyle/examples/pushbutton/__main__.py
qtvscodestyle/examples/switching_theme/__init__.py
qtvscodestyle/examples/switching_theme/__main__.py
qtvscodestyle/examples/theme_icon/__init__.py
qtvscodestyle/examples/theme_icon/__main__.py
qtvscodestyle/examples/widget_gallery/__init__.py
qtvscodestyle/examples/widget_gallery/__main__.py
qtvscodestyle/examples/widget_gallery/ui/__init__.py
qtvscodestyle/examples/widget_gallery/ui/dock.py
qtvscodestyle/examples/widget_gallery/ui/home.py
qtvscodestyle/examples/widget_gallery/ui/main_ui.py
qtvscodestyle/fonts/__init__.py
qtvscodestyle/fonts/fa-brands-400.ttf
qtvscodestyle/fonts/fa-regular-400.ttf
qtvscodestyle/fonts/fa-solid-900.ttf
qtvscodestyle/q_icon/__init__.py
qtvscodestyle/q_icon/iconic_font.py
qtvscodestyle/q_icon/svg.py
qtvscodestyle/qtpy/.git
qtvscodestyle/qtpy/.gitignore
qtvscodestyle/qtpy/LICENSE
qtvscodestyle/qtpy/QtCore/__init__.py
qtvscodestyle/qtpy/QtGui/__init__.py
qtvscodestyle/qtpy/QtSvg/__init__.py
qtvscodestyle/qtpy/QtWidgets/__init__.py
qtvscodestyle/qtpy/README.md
qtvscodestyle/qtpy/__init__.py
qtvscodestyle/qtpy/qt_compat.py
qtvscodestyle/qtpy/qt_version.py
qtvscodestyle/resource_builder/__init__.py
qtvscodestyle/resource_builder/__main__.py
qtvscodestyle/stylesheet/__init__.py
qtvscodestyle/stylesheet/build.py
qtvscodestyle/stylesheet/icons/__init__.py
qtvscodestyle/stylesheet/icons/corner_button.svg
qtvscodestyle/stylesheet/icons/flip_to_front.svg
qtvscodestyle-0.1.1.dist-info/LICENSE.txt
qtvscodestyle-0.1.1.dist-info/WHEEL
qtvscodestyle-0.1.1.dist-info/METADATA
qtvscodestyle-0.1.1.dist-info/RECORD
