Metadata-Version: 2.1
Name: qtvscodestyle
Version: 0.1.1
Summary: VS Code Style for PySide, PyQt.
Home-page: https://github.com/5yutan5/QtVSCodeStyle
License: MIT
Keywords: qt,stylesheets,vscode
Author: Yunosuke Ohsugi
Author-email: 63651161+5yutan5@users.noreply.github.com
Requires-Python: >=3.7,<4.0
Classifier: Environment :: X11 Applications :: Qt
Classifier: License :: OSI Approved :: MIT License
Classifier: Natural Language :: English
Classifier: Operating System :: MacOS
Classifier: Operating System :: Microsoft :: Windows
Classifier: Programming Language :: Python :: 3
Classifier: Programming Language :: Python :: 3.7
Classifier: Programming Language :: Python :: 3.8
Classifier: Programming Language :: Python :: 3.9
Classifier: Topic :: Software Development :: Libraries :: Python Modules
Project-URL: Repository, https://github.com/5yutan5/QtVSCodeStyle
